soap2rest/__init__.py
soap2rest/api.py
soap2rest/cli.py
soap2rest-0.1.0.dist-info/licenses/LICENSE
soap2rest-0.1.0.dist-info/METADATA
soap2rest-0.1.0.dist-info/WHEEL
soap2rest-0.1.0.dist-info/entry_points.txt
soap2rest-0.1.0.dist-info/top_level.txt
soap2rest-0.1.0.dist-info/RECORD
