Metadata-Version: 2.4
Name: soap2rest
Version: 0.1.0
Summary: Convert any SOAP WSDL service to a REST API using FastAPI
Author-email: Ashish <you@example.com>
Maintainer-email: Ashish <you@example.com>
License-Expression: MIT
Project-URL: Homepage, https://github.com/yourusername/soap2rest
Project-URL: Documentation, https://github.com/yourusername/soap2rest#readme
Project-URL: Repository, https://github.com/yourusername/soap2rest
Project-URL: Issues, https://github.com/yourusername/soap2rest/issues
Project-URL: Bug Tracker, https://github.com/yourusername/soap2rest/issues
Keywords: soap,rest,api,wsdl,fastapi,conversion,web-service,http,soap-to-rest
Classifier: Development Status :: 4 - Beta
Classifier: Intended Audience :: Developers
Classifier: Operating System :: OS Independent
Classifier: Programming Language :: Python :: 3
Classifier: Programming Language :: Python :: 3.8
Classifier: Programming Language :: Python :: 3.9
Classifier: Programming Language :: Python :: 3.10
Classifier: Programming Language :: Python :: 3.11
Classifier: Programming Language :: Python :: 3.12
Classifier: Topic :: Internet :: WWW/HTTP :: HTTP Servers
Classifier: Topic :: Software Development :: Libraries :: Python Modules
Classifier: Topic :: Software Development :: Libraries :: Application Frameworks
Classifier: Framework :: FastAPI
Requires-Python: >=3.8
License-File: LICENSE
Requires-Dist: fastapi<1.0,>=0.104.0
Requires-Dist: uvicorn[standard]<1.0,>=0.24.0
Requires-Dist: zeep<5.0,>=4.2.0
Requires-Dist: pydantic<3.0,>=2.0.0
Requires-Dist: anyio<4.0,>=3.0.0
Requires-Dist: requests>=2.28.0
Provides-Extra: dev
Requires-Dist: pytest>=7.0.0; extra == "dev"
Requires-Dist: pytest-asyncio>=0.21.0; extra == "dev"
Requires-Dist: httpx>=0.24.0; extra == "dev"
Requires-Dist: build>=0.10.0; extra == "dev"
Requires-Dist: twine>=4.0.0; extra == "dev"
Dynamic: license-file
